abcd_yt98/__init__.py
abcd_yt98/addone.py
abcd_yt98/two.py
abcd_yt98-1.0.0.dist-info/LICENSE
abcd_yt98-1.0.0.dist-info/METADATA
abcd_yt98-1.0.0.dist-info/WHEEL
abcd_yt98-1.0.0.dist-info/top_level.txt
abcd_yt98-1.0.0.dist-info/RECORD
